<?xml version="1.0" encoding="utf-8" ?>
<dwsync>
<file name="az.mo" server="fagle.gotoftp4.com/wwwroot/" local="130971199800000000" remote="130971199800000000" Dst="-1" />
<file name="az.po" server="fagle.gotoftp4.com/wwwroot/" local="130971199800000000" remote="130971199800000000" Dst="-1" />
<file name="bs_BA.mo" server="fagle.gotoftp4.com/wwwroot/" local="130971199800000000" remote="130971199800000000" Dst="-1" />
<file name="bs_BA.po" server="fagle.gotoftp4.com/wwwroot/" local="130971199800000000" remote="130971199800000000" Dst="-1" />
<file name="coraline.pot" server="fagle.gotoftp4.com/wwwroot/" local="130971199800000000" remote="130971199800000000" Dst="-1" />
<file name="de_DE.mo" server="fagle.gotoftp4.com/wwwroot/" local="130971199800000000" remote="130971199800000000" Dst="-1" />
<file name="de_DE.po" server="fagle.gotoftp4.com/wwwroot/" local="130971199800000000" remote="130971199800000000" Dst="-1" />
<file name="el-po.mo" server="fagle.gotoftp4.com/wwwroot/" local="130971199800000000" remote="130971199800000000" Dst="-1" />
<file name="el-po.po" server="fagle.gotoftp4.com/wwwroot/" local="130971199800000000" remote="130971199800000000" Dst="-1" />
<file name="es_ES.mo" server="fagle.gotoftp4.com/wwwroot/" local="130971199800000000" remote="130971199800000000" Dst="-1" />
<file name="es_ES.po" server="fagle.gotoftp4.com/wwwroot/" local="130971199800000000" remote="130971199800000000" Dst="-1" />
<file name="fa_IR.mo" server="fagle.gotoftp4.com/wwwroot/" local="130971199800000000" remote="130971199800000000" Dst="-1" />
<file name="fa_IR.po" server="fagle.gotoftp4.com/wwwroot/" local="130971199800000000" remote="130971199800000000" Dst="-1" />
<file name="fr_CA.mo" server="fagle.gotoftp4.com/wwwroot/" local="130971199800000000" remote="130971199800000000" Dst="-1" />
<file name="fr_CA.po" server="fagle.gotoftp4.com/wwwroot/" local="130971199800000000" remote="130971199800000000" Dst="-1" />
<file name="fr_FR.mo" server="fagle.gotoftp4.com/wwwroot/" local="130971199800000000" remote="130971199800000000" Dst="-1" />
<file name="fr_FR.po" server="fagle.gotoftp4.com/wwwroot/" local="130971199800000000" remote="130971199800000000" Dst="-1" />
<file name="ga.mo" server="fagle.gotoftp4.com/wwwroot/" local="130971199800000000" remote="130971199800000000" Dst="-1" />
<file name="ga.po" server="fagle.gotoftp4.com/wwwroot/" local="130971199800000000" remote="130971199800000000" Dst="-1" />
<file name="gl_ES.mo" server="fagle.gotoftp4.com/wwwroot/" local="130971199800000000" remote="130971199800000000" Dst="-1" />
<file name="gl_ES.po" server="fagle.gotoftp4.com/wwwroot/" local="130971199800000000" remote="130971199800000000" Dst="-1" />
<file name="he_IL.mo" server="fagle.gotoftp4.com/wwwroot/" local="130971199800000000" remote="130971199800000000" Dst="-1" />
<file name="he_IL.po" server="fagle.gotoftp4.com/wwwroot/" local="130971199800000000" remote="130971199800000000" Dst="-1" />
<file name="hu_HU.mo" server="fagle.gotoftp4.com/wwwroot/" local="130971199800000000" remote="130971199800000000" Dst="-1" />
<file name="hu_HU.po" server="fagle.gotoftp4.com/wwwroot/" local="130971199800000000" remote="130971199800000000" Dst="-1" />
<file name="it_IT.mo" server="fagle.gotoftp4.com/wwwroot/" local="130971199800000000" remote="130971199800000000" Dst="-1" />
<file name="it_IT.po" server="fagle.gotoftp4.com/wwwroot/" local="130971199800000000" remote="130971199800000000" Dst="-1" />
<file name="ja.mo" server="fagle.gotoftp4.com/wwwroot/" local="130971199800000000" remote="130971199800000000" Dst="-1" />
<file name="ja.po" server="fagle.gotoftp4.com/wwwroot/" local="130971199800000000" remote="130971199800000000" Dst="-1" />
<file name="ko_KR.mo" server="fagle.gotoftp4.com/wwwroot/" local="130971199800000000" remote="130971199800000000" Dst="-1" />
<file name="ko_KR.po" server="fagle.gotoftp4.com/wwwroot/" local="130971199800000000" remote="130971199800000000" Dst="-1" />
<file name="nl_NL.mo" server="fagle.gotoftp4.com/wwwroot/" local="130971199800000000" remote="130971199800000000" Dst="-1" />
<file name="nl_NL.po" server="fagle.gotoftp4.com/wwwroot/" local="130971199800000000" remote="130971199800000000" Dst="-1" />
<file name="pt_BR.mo" server="fagle.gotoftp4.com/wwwroot/" local="130971199800000000" remote="130971199800000000" Dst="-1" />
<file name="pt_BR.po" server="fagle.gotoftp4.com/wwwroot/" local="130971199800000000" remote="130971199800000000" Dst="-1" />
<file name="sq.mo" server="fagle.gotoftp4.com/wwwroot/" local="130971199800000000" remote="130971199800000000" Dst="-1" />
<file name="sq.po" server="fagle.gotoftp4.com/wwwroot/" local="130971199800000000" remote="130971199800000000" Dst="-1" />
<file name="sr_RS.mo" server="fagle.gotoftp4.com/wwwroot/" local="130971199800000000" remote="130971199800000000" Dst="-1" />
<file name="sr_RS.po" server="fagle.gotoftp4.com/wwwroot/" local="130971199800000000" remote="130971199800000000" Dst="-1" />
</dwsync>